trackidnet/client.py
trackidnet/models.py
trackidnet-0.0.3.dist-info/METADATA
trackidnet-0.0.3.dist-info/WHEEL
trackidnet-0.0.3.dist-info/RECORD
