Metadata-Version: 2.4
Name: trackidnet
Version: 0.0.3
Summary: Python API client for TrackID.net
Author-email: Jacopo Carrani <jacopocarrani@gmail.com>
Requires-Python: >=3.11
Requires-Dist: httpx>=0.27.0
Requires-Dist: pydantic>=2.0.0
Requires-Dist: ruff>=0.14.2
Provides-Extra: dev
Requires-Dist: pytest-cov>=4.1.0; extra == 'dev'
Requires-Dist: pytest>=8.0.0; extra == 'dev'
Requires-Dist: ruff>=0.3.0; extra == 'dev'
